{
  "presets" : [
    {
      "id" : 0,
      "useIntra8x8": 1,
      "transformMode": 1,
      "scalingMatrixMode": 0,
      "numBFrames": 2,
      "motionEstimationInLA" : 1,
      "useDynamicB": 0,
      "useMMCO": 0,
      "pixelPrecisionP": 1,
      "pixelPrecisionBr": 1,
      "pixelPrecisionB": 1,
      "fastSubPelMode": 1,
      "intraQpDelta": 0,
      "globalMeCalc": 0,
      "useAllListsB": 0,
      "adaptiveDeblocking": 0,
      "ME_typeP": 2,
      "ME_typeB": 2,
      "ME_typeBRef": 2,
      "motionEstimationShortcuts": 31,
      "interPSearchModes.use16x16": 1,
      "interPSearchModes.use16x8": 0,
      "interPSearchModes.use8x16": 0,
      "interBRSearchModes.use16x16": 1,
      "interBRSearchModes.use16x8": 0,
      "interBRSearchModes.use8x16": 0,
      "interBSearchModes.use16x16": 1,
      "interBSearchModes.use16x8": 0,
      "interBSearchModes.use8x16": 0,
      "nbReferenceFramesP": 1,
      "nbReferenceFramesBL0": 1,
      "nbReferenceFramesBL1": 1,
      "chromaDecision": 0,
      "useIntraSearchP": 0,
      "useIntraSearchBr": 0,
      "useIntraSearchB": 0,
      "predIntraDecisionI": 0,
      "predIntraDecisionP": 0,
      "useDcCompensatedSAD": 0,
      "HMEonRefOnly": 0,
      "HMEonListL1": 1,
      "useWobbleDetection": 0,
      "TrellisQuantization": 0,
      "optimizeDecisionsInSSIM": 0,
      "useRdoShortcuts": 0,
      "decisionTypeI": 0,
      "decisionTypeP": 0,
      "decisionPartInterP": 0,
      "decisionPredInterP": 0,
      "decisionTypeB": 0,
      "decisionPartInterB": 0,
      "weightedPrediction": 0,
      "reencodeInterFrame": 0,
      "useIntraPredShortcut": 1,
      "rdstqLambdaRescale": 1,
      "useAdaptSearchRangeTD": 0,
      "dequantType": 9,
      "rdstqMode": 2,
      "rdstqRateCstr": 2,
      "minQuantizer": 6,
      "maxQuantizer": 51,
      "useStaticZones": 0
    }
    ,
    {
      "id": 1,
      "pixelPrecisionP": 2,
      "interPSearchModes.use16x8": 1,
      "interPSearchModes.use8x16": 1,
      "useIntraSearchP": 1
    },
    {
      "id": 2,
      "pixelPrecisionP": 4,
      "pixelPrecisionBr": 4,
      "pixelPrecisionB": 4
    },
    {
      "id": 3,
      "predIntraDecisionI": 1,
      "predIntraDecisionP": 1,
      "decisionTypeI": 1,
      "decisionTypeP": 1,
      "decisionPartInterP": 1,
      "decisionPredInterP": 1
    },
    {
      "id": 4,
      "ME_typeP": 6,
      "transformMode": 3,
      "scalingMatrixMode": 5,
      "weightedPrediction": 1
    },
    {
      "id": 5,
      "numBFrames": 3,
      "useDcCompensatedSAD": 1,
      "ME_typeBRef": 6
    },
    {
      "id": 6,
      "useIntraSearchBr": 1,
      "intraQpDelta": 8,
      "globalMeCalc": 1,
      "useWobbleDetection": 4,
      "adaptiveDeblocking": 5
    },    
    {
      "id": 7,
      "interBRSearchModes.use16x8": 1,
      "interBRSearchModes.use8x16": 1
    },
    {
      "id": 8,
      "fastSubPelMode": 0,
      "ME_typeB": 6
    },
    {
      "id": 9,
      "interBSearchModes.use16x8": 1,
      "interBSearchModes.use8x16": 1
    },
    {
      "id": 10,
      "useIntraPredShortcut": 0,
      "useIntraSearchB": 2
    },
    {
      "id": 11,
      "numBFrames": 7,
      "useDynamicB": 1,
      "useMMCO": 1,
      "decisionTypeP": 2,
      "transformMode": 2,
      "dequantType": 9,
      "rdstqMode": 0,
      "rdstqRateCstr": 0,
      "reencodeInterFrame": 2
    },
    {
      "id": 12,
      "nbReferenceFramesP": 2
    },
    {
      "id": 13,
      "intraQpDelta": 0,
      "useAllListsB": 1,
      "useRdoShortcuts": 2,
      "decisionTypeI": 3,
      "decisionTypeP": 3
    },
    {
      "id": 14,
      "useRdoShortcuts": 0
    },
    {
      "id": 15,
      "decisionPartInterP": 3,
      "transformMode": 4,
      "chromaDecision": 1
    },
    {
      "id": 16,
      "nbReferenceFramesP": 3,
      "useRdoShortcuts": 7,
      "decisionTypeB": 3
    },
    {
      "id": 17,
      "useRdoShortcuts": 2
    },
    {
      "id": 18,
      "useWobbleDetection": 0,
      "optimizeDecisionsInSSIM": 7,
      "useRdoShortcuts": 0,
      "ME_typeP": 3,
      "ME_typeBRef": 3
    },
    {
      "id": 19,
      "nbReferenceFramesBL0": 2,
      "decisionPartInterB": 3
    },
    {
      "id": 20,
       "TrellisQuantization": 3
    }
  ],
  "checksum" : {}
}
